{
  "todos": [
    {
      "id": "1668700669524",
      "title": "dad",
      "date": "2022-11-17T15:57:49.524Z",
      "isCompleted": false
    },
    {
      "id": "1669137095069",
      "title": "Jjj",
      "date": "2022-11-22T17:11:35.069Z",
      "isCompleted": false
    },
    {
      "id": "1669137335898",
      "title": "KGg",
      "date": "2022-11-22T17:15:35.898Z",
      "isCompleted": false
    },
    {
      "id": "1669306421684",
      "title": "Fourth",
      "date": "2022-11-24T16:13:41.684Z",
      "isCompleted": false
    },
    {
      "id": "1669306515164",
      "title": "Fifth",
      "date": "2022-11-24T16:15:15.164Z",
      "isCompleted": false
    },
    {
      "id": "1669306550166",
      "title": "Sixth",
      "date": "2022-11-24T16:15:50.166Z",
      "isCompleted": false
    },
    {
      "id": "1669306555495",
      "title": "Seventh",
      "date": "2022-11-24T16:15:55.495Z",
      "isCompleted": false
    },
    {
      "id": "1669310712572",
      "title": "ahdqimx",
      "date": "2022-11-24T17:25:12.572Z",
      "isCompleted": false
    },
    {
      "id": "1669311205225",
      "title": "ssbbg",
      "date": "2022-11-24T17:33:25.225Z",
      "isCompleted": false
    },
    {
      "id": "1669311293951",
      "title": "ssbbgk",
      "date": "2022-11-24T17:34:53.951Z",
      "isCompleted": false
    },
    {
      "id": "1669311400333",
      "title": "dad",
      "date": "2022-11-24T17:36:40.333Z",
      "isCompleted": false
    },
    {
      "id": "1669312257270",
      "title": "Jjjq",
      "date": "2022-11-24T17:50:57.270Z",
      "isCompleted": false
    }
  ],
  "profile": {
    "name": "typicode"
  }
}